arcgis_mcp.py
arcgis_mcp_server-1.1.5.dist-info/METADATA
arcgis_mcp_server-1.1.5.dist-info/WHEEL
arcgis_mcp_server-1.1.5.dist-info/top_level.txt
arcgis_mcp_server-1.1.5.dist-info/RECORD
