Metadata-Version: 2.4
Name: arcgis-mcp-server
Version: 1.1.5
Summary: Intelligent ArcGIS content search for Portal and Online.
Home-page: https://github.com/esrisaudiarabia/esrisaudiarabia-mcp
Author: Esri Saudi Arabia
License: MIT
Requires-Dist: arcgis
Requires-Dist: beautifulsoup4
Requires-Dist: fastmcp
Requires-Dist: python-dotenv
